Metadata-Version: 1.0
Name: django-sentry-400-middleware
Version: 0.3.0
Summary: Django middleware to log 400 level errors to Sentry.
Home-page: https://github.com/ArtProcessors/django-sentry-400-middleware
Author: Art Processors
Author-email: operations@artprocessors.net
License: UNKNOWN
Platform: UNKNOWN
